<?xml version="1.0" encoding="utf-8"?>
<!-- This list contains names/words with specific casing - and specific to English only -->
<names>
  <name>Abbie</name>
  <name>Abi</name>
  <name>Aimee</name>
  <name>Ashleigh</name>
  <name>Bethan</name>
  <name>Ciara</name>
  <name>Faye</name>
  <name>Finn</name>
  <name>Freya</name>
  <name>Holly</name>
  <name>Imogen</name>
  <name>Ingvarsson</name>
  <name>Jade</name>
  <name>Kai</name>
  <name>Kayleigh</name>
  <name>Kian</name>
  <name>Kieran</name>
  <name>Kirsty</name>
  <name>Leah</name>
  <name>Lily</name>
  <name>Mark</name>
  <name>Milly</name>
  <name>Mollie</name>
  <name>Niamh</name>
  <name>Poppy</name>
  <name>Rachael</name>
  <name>Reece</name>
  <name>Rhiannon</name>
  <name>Rhys</name>
  <name>Rob</name>
  <name>Robyn</name>
  <name>Rose</name>
  <name>Tia</name>
  <name>Tom</name>
  <blacklist>
    <name></name>
  </blacklist>
</names>